{"kind":"identitytoolkit#DownloadAccountResponse","users":[{"localId":"3xm1umlOxtSUxlt9Debc1Va4W5CH","createdAt":"1773508532151","lastLoginAt":"1773508892809","displayName":"Samuel Caetite","passwordHash":"fakeHash:salt=fakeSaltRteTAjgY82XpgHSYQ9Bm:password=senha123","salt":"fakeSaltRteTAjgY82XpgHSYQ9Bm","passwordUpdatedAt":1773508722441,"customAttributes":"{\"role\":\"owner\"}","providerUserInfo":[{"providerId":"password","email":"srcaetite@gmail.com","federatedId":"srcaetite@gmail.com","rawId":"srcaetite@gmail.com","displayName":"Samuel Caetite"}],"validSince":"1773508722","email":"srcaetite@gmail.com","emailVerified":false,"disabled":false,"lastRefreshAt":"2026-03-14T17:21:32.809Z"}]}